[
  {
    "id": 1,
    "front": "Hotel",
    "back": "Hotel",
    "frontExample": "This hotel is brand new.",
    "backExample": "Ten hotel jest całkiem nowy.",
    "phonetic": "/həʊˈtel/",
    "remembered": false
  },
  {
    "id": 2,
    "front": "Reception",
    "back": "Recepcja",
    "frontExample": "Ask for a city map at reception.",
    "backExample": "Poproś w recepcji o mapę miasta.",
    "phonetic": "/rɪˈsɛpʃən/",
    "remembered": false
  },
  {
    "id": 3,
    "front": "Receptionist",
    "back": "Recepcjonista/Recepcjonistka",
    "frontExample": "The receptionist spoke very clearly.",
    "backExample": "Recepcjonistka mówiła bardzo wyraźnie.",
    "phonetic": "/rɪˈsɛpʃənɪst/",
    "remembered": false
  },
  {
    "id": 4,
    "front": "Guest",
    "back": "Gość",
    "frontExample": "Each guest gets a welcome cookie.",
    "backExample": "Każdy gość dostaje powitalne ciastko.",
    "phonetic": "/ɡest/",
    "remembered": false
  },
  {
    "id": 5,
    "front": "Room",
    "back": "Pokój",
    "frontExample": "Our room faces the garden.",
    "backExample": "Nasz pokój wychodzi na ogród.",
    "phonetic": "/rʊm/",
    "remembered": false
  },
  {
    "id": 6,
    "front": "Room key",
    "back": "Klucz do pokoju",
    "frontExample": "Please return your room key at checkout.",
    "backExample": "Proszę zwrócić klucz do pokoju przy wymeldowaniu.",
    "phonetic": "/ruːm kiː/",
    "remembered": false
  },
  {
    "id": 7,
    "front": "Key card",
    "back": "Karta-klucz do pokoju",
    "frontExample": "Your key card also opens the gym.",
    "backExample": "Twoja karta do pokoju otwiera też siłownię.",
    "phonetic": "/ˈkiː kɑːrd/",
    "remembered": false
  },
  {
    "id": 8,
    "front": "Reservation",
    "back": "Rezerwacja",
    "frontExample": "I changed my reservation to next week.",
    "backExample": "Przełożyłem rezerwację na przyszły tydzień.",
    "phonetic": "/rɪˈzɛrvəˈʃən/",
    "remembered": false
  },
  {
    "id": 9,
    "front": "Booking",
    "back": "Rezerwacja",
    "frontExample": "My booking includes free parking.",
    "backExample": "Moja rezerwacja obejmuje darmowy parking.",
    "phonetic": "/ˈboʊkɪŋ/",
    "remembered": false
  },
  {
    "id": 10,
    "front": "Check-in",
    "back": "Zameldować się",
    "frontExample": "Online check-in saved us time.",
    "backExample": "Zameldowanie online oszczędziło nam czas.",
    "phonetic": "/tʃɛk ˈɪn/",
    "remembered": false
  },
  {
    "id": 11,
    "front": "Check-out",
    "back": "Wymeldować się",
    "frontExample": "Late check-out costs ten dollars.",
    "backExample": "Późne wymeldowanie kosztuje dziesięć dolarów.",
    "phonetic": "/tʃɛk ˈaʊt/",
    "remembered": false
  },
  {
    "id": 12,
    "front": "Lobby",
    "back": "Hol",
    "frontExample": "We waited for our taxi in the lobby.",
    "backExample": "Czekaliśmy na taksówkę w holu.",
    "phonetic": "/ˈloʊbi/",
    "remembered": false
  },
  {
    "id": 13,
    "front": "Elevator (UK: lift)",
    "back": "winda",
    "frontExample": "The elevator is out of order.",
    "backExample": "Winda jest nieczynna.",
    "phonetic": "/ˈelɪveɪtər/",
    "remembered": false
  },
  {
    "id": 14,
    "front": "Stairs",
    "back": "Schody",
    "frontExample": "The stairs are to the left of the lobby.",
    "backExample": "Schody są na lewo od holu.",
    "phonetic": "/stɛəz/",
    "remembered": false
  },
  {
    "id": 15,
    "front": "Floor",
    "back": "Piętro",
    "frontExample": "The spa is on the fourth floor.",
    "backExample": "Spa jest na czwartym piętrze.",
    "phonetic": "/flɔr/",
    "remembered": false
  },
  {
    "id": 16,
    "front": "Single room",
    "back": "Pokój jednoosobowy",
    "frontExample": "A single room is fine for me.",
    "backExample": "Pokój jednoosobowy mi wystarczy.",
    "phonetic": "/ˈsɪnɡəl ˈrʊm/",
    "remembered": false
  },
  {
    "id": 17,
    "front": "Double room",
    "back": "Pokój dwuosobowy",
    "frontExample": "We requested a double room with a view.",
    "backExample": "Poprosiliśmy o pokój dwuosobowy z widokiem.",
    "phonetic": "/ˈdʌbl ˈrʊm/",
    "remembered": false
  },
  {
    "id": 18,
    "front": "Twin room",
    "back": "Pokój z dwoma łóżkami",
    "frontExample": "A twin room works better for us.",
    "backExample": "Pokój z dwoma łóżkami będzie dla nas lepszy.",
    "phonetic": "/ˈtwɪn ˈrʊm/",
    "remembered": false
  },
  {
    "id": 19,
    "front": "Suite",
    "back": "Apartament",
    "frontExample": "They upgraded us to a suite.",
    "backExample": "Przydzielono nam apartament.",
    "phonetic": "/suɪt/",
    "remembered": false
  },
  {
    "id": 20,
    "front": "Bed",
    "back": "Łóżko",
    "frontExample": "The bed is wider than I expected.",
    "backExample": "Łóżko jest szersze, niż się spodziewałem.",
    "phonetic": "/bed/",
    "remembered": false
  },
  {
    "id": 21,
    "front": "Blanket",
    "back": "Koc",
    "frontExample": "Could I have an extra blanket?",
    "backExample": "Czy mogę dostać dodatkowy koc?",
    "phonetic": "/ˈblænkɪt/",
    "remembered": false
  },
  {
    "id": 22,
    "front": "Pillow",
    "back": "Poduszka",
    "frontExample": "This pillow is too soft for me.",
    "backExample": "Ta poduszka jest dla mnie za miękka.",
    "phonetic": "/ˈpɪləʊ/",
    "remembered": false
  },
  {
    "id": 23,
    "front": "Towel",
    "back": "Ręcznik",
    "frontExample": "Fresh towels arrive every morning.",
    "backExample": "Świeże ręczniki są dostarczane każdego ranka.",
    "phonetic": "/ˈtəʊl/",
    "remembered": false
  },
  {
    "id": 24,
    "front": "Bathroom",
    "back": "Łazienka",
    "frontExample": "The bathroom has heated floors.",
    "backExample": "Łazienka ma podgrzewaną podłogę.",
    "phonetic": "/ˈbæθrʊm/",
    "remembered": false
  },
  {
    "id": 25,
    "front": "Shower",
    "back": "Prysznic",
    "frontExample": "The shower takes a minute to warm up.",
    "backExample": "Prysznic potrzebuje minuty, żeby się nagrzać.",
    "phonetic": "/ʃaʊər/",
    "remembered": false
  },
  {
    "id": 26,
    "front": "Bathtub",
    "back": "Wanna",
    "frontExample": "The bathtub has Jacuzzi jets.",
    "backExample": "Wanna ma dysze jak w jacuzzi.",
    "phonetic": "/ˈbæθtʌb/",
    "remembered": false
  },
  {
    "id": 27,
    "front": "Toilet",
    "back": "Toaleta",
    "frontExample": "The toilet flush is broken.",
    "backExample": "Przycisk spłuczki jest zepsuty.",
    "phonetic": "/ˈtoɪlɪt/",
    "remembered": false
  },
  {
    "id": 28,
    "front": "Sink",
    "back": "Umywalka",
    "frontExample": "The sink is clogged again.",
    "backExample": "Umywalka znowu jest zapchana.",
    "phonetic": "/sɪŋk/",
    "remembered": false
  },
  {
    "id": 29,
    "front": "Soap",
    "back": "Mydło",
    "frontExample": "We ran out of soap in the room.",
    "backExample": "Skończyło nam się mydło w pokoju.",
    "phonetic": "/səʊp/",
    "remembered": false
  },
  {
    "id": 30,
    "front": "Shampoo",
    "back": "Szampon",
    "frontExample": "Do you have travel-size shampoo?",
    "backExample": "Macie szampon w małych butelkach?",
    "phonetic": "/ʃæmpən/",
    "remembered": false
  },
  {
    "id": 31,
    "front": "Hairdryer",
    "back": "Suszarka do włosów",
    "frontExample": "The hairdryer stopped working.",
    "backExample": "Suszarka do włosów przestała działać.",
    "phonetic": "/ˈhɛərdʌɪər/",
    "remembered": false
  },
  {
    "id": 32,
    "front": "Air conditioning",
    "back": "Klimatyzacja",
    "frontExample": "Please turn on the air conditioning.",
    "backExample": "Proszę włączyć klimatyzację.",
    "phonetic": "/ˈeər ˈkɑndɪˈʃən/",
    "remembered": false
  },
  {
    "id": 33,
    "front": "Heating",
    "back": "Ogrzewanie",
    "frontExample": "Can you lower the heating at night?",
    "backExample": "Czy możecie zmniejszyć ogrzewanie w nocy?",
    "phonetic": "/ˈheɪtɪŋ/",
    "remembered": false
  },
  {
    "id": 34,
    "front": "Wi-Fi",
    "back": "Wi-Fi",
    "frontExample": "What's the Wi‑Fi speed here?",
    "backExample": "Jaka jest tu prędkość Wi‑Fi?",
    "phonetic": "/ˈwifaɪ/",
    "remembered": false
  },
  {
    "id": 35,
    "front": "Password",
    "back": "Hasło",
    "frontExample": "Please text me the Wi‑Fi password.",
    "backExample": "Wyślij mi proszę hasło do Wi‑Fi.",
    "phonetic": "/ˈpɑswərd/",
    "remembered": false
  },
  {
    "id": 36,
    "front": "Breakfast",
    "back": "Śniadanie",
    "frontExample": "We skipped breakfast to catch the train.",
    "backExample": "Pominęliśmy śniadanie, żeby zdążyć na pociąg.",
    "phonetic": "/ˈbreɪkfəst/",
    "remembered": false
  },
  {
    "id": 37,
    "front": "Buffet",
    "back": "Bufet",
    "frontExample": "The buffet opens at 7 a.m.",
    "backExample": "Bufet otwiera się o 7 rano.",
    "phonetic": "/ˈbʌfɪt/",
    "remembered": false
  },
  {
    "id": 38,
    "front": "Restaurant",
    "back": "Restauracja",
    "frontExample": "The restaurant closes at 11 p.m.",
    "backExample": "Restauracja zamyka się o 23:00.",
    "phonetic": "/rɪˈstɔrənt/",
    "remembered": false
  },
  {
    "id": 39,
    "front": "Room service",
    "back": "Obsługa pokojowa",
    "frontExample": "Room service is available 24 hours.",
    "backExample": "Obsługa pokojowa jest dostępna przez 24 godziny.",
    "phonetic": "/ˈrʊm ˈsɜrvɪs/",
    "remembered": false
  },
  {
    "id": 40,
    "front": "Cleaning service",
    "back": "Serwis sprzątający",
    "frontExample": "The cleaning service comes every other day.",
    "backExample": "Serwis sprzątający przychodzi co drugi dzień.",
    "phonetic": "/ˈkliniŋ ˈsɜrvɪs/",
    "remembered": false
  },
  {
    "id": 41,
    "front": "Housekeeping",
    "back": "Personel sprzątający",
    "frontExample": "Housekeeping left fresh water in the room.",
    "backExample": "Personel sprzątający zostawił świeżą wodę w pokoju.",
    "phonetic": "/ˈhaʊsˌkeɪpɪŋ/",
    "remembered": false
  },
  {
    "id": 42,
    "front": "Laundry",
    "back": "Pralnia",
    "frontExample": "Laundry takes two days during weekends.",
    "backExample": "Pralnia zajmuje dwa dni w weekendy.",
    "phonetic": "/ˈlɔndri/",
    "remembered": false
  },
  {
    "id": 43,
    "front": "Mini-bar",
    "back": "Mini barek",
    "frontExample": "The mini-bar was restocked this morning.",
    "backExample": "Minibar został uzupełniony dziś rano.",
    "phonetic": "/ˈmɪnɪ ˈbɑr/",
    "remembered": false
  },
  {
    "id": 44,
    "front": "Safe",
    "back": "Sejf",
    "frontExample": "We locked our passports in the safe.",
    "backExample": "Schowaliśmy paszporty do sejfu.",
    "phonetic": "/seɪf/",
    "remembered": false
  },
  {
    "id": 45,
    "front": "TV",
    "back": "Telewizor",
    "frontExample": "The TV doesn't have English channels.",
    "backExample": "Telewizor nie ma angielskich kanałów.",
    "phonetic": "/tɛlɪˈvɪzər/",
    "remembered": false
  },
  {
    "id": 46,
    "front": "Remote control",
    "back": "Pilot do telewizora",
    "frontExample": "The remote control needs new batteries.",
    "backExample": "Pilot do telewizora potrzebuje nowych baterii.",
    "phonetic": "/rɪˈməʊt ˈkəntroʊl/",
    "remembered": false
  },
  {
    "id": 47,
    "front": "Telephone",
    "back": "Telefon",
    "frontExample": "Use the telephone to call the front desk.",
    "backExample": "Użyj telefonu, aby zadzwonić na recepcję.",
    "phonetic": "/ˈtelɪfən/",
    "remembered": false
  },
  {
    "id": 48,
    "front": "Wake-up call",
    "back": "Budzenie telefoniczne",
    "frontExample": "Could I get a wake-up call at 6:30?",
    "backExample": "Czy mogę prosić o pobudkę o 6:30?",
    "phonetic": "/ˈweɪk ˈʌp ˈkɔl/",
    "remembered": false
  },
  {
    "id": 49,
    "front": "No smoking",
    "back": "Zakaz palenia",
    "frontExample": "There is a no smoking sign on the door.",
    "backExample": "Na drzwiach jest znak zakazu palenia.",
    "phonetic": "/noʊ ˈsmoʊkɪŋ/",
    "remembered": false
  },
  {
    "id": 50,
    "front": "Non-smoking room",
    "back": "Pokój dla niepalących",
    "frontExample": "I asked for a non-smoking room.",
    "backExample": "Poprosiłem o pokój dla niepalących.",
    "phonetic": "/ˈnɑn ˈsmoʊkɪŋ ˈrʊm/",
    "remembered": false
  },
  {
    "id": 51,
    "front": "Smoking room",
    "back": "Palarnia/Pokój dla palących",
    "frontExample": "They still offer a smoking room on the top floor.",
    "backExample": "Nadal oferują pokój dla palących na najwyższym piętrze.",
    "phonetic": "/ˈsmoʊkɪŋ ˈrʊm/",
    "remembered": false
  },
  {
    "id": 52,
    "front": "Pets allowed",
    "back": "Zwierzęta dozwolone",
    "frontExample": "Pets are allowed for an extra fee.",
    "backExample": "Zwierzęta są dozwolone za dodatkową opłatą.",
    "phonetic": "/pets ˈəˈlaʊd/",
    "remembered": false
  },
  {
    "id": 53,
    "front": "Luggage",
    "back": "Bagaż",
    "frontExample": "My luggage didn't arrive with the flight.",
    "backExample": "Mój bagaż nie przyleciał z lotem.",
    "phonetic": "/ˈlʌɡɪdʒ/",
    "remembered": false
  },
  {
    "id": 54,
    "front": "Luggage storage",
    "back": "Przechowalnia bagażu",
    "frontExample": "We left our bags in the luggage storage.",
    "backExample": "Zostawiliśmy torby w przechowalni bagażu.",
    "phonetic": "/ˈlʌɡɪdʒ ˈstɔrɪdʒ/",
    "remembered": false
  },
  {
    "id": 55,
    "front": "Concierge",
    "back": "Konsjerż",
    "frontExample": "The concierge booked us opera tickets.",
    "backExample": "Konsjerż zarezerwował nam bilety do opery.",
    "phonetic": "/kɑnsˈʒɪər/",
    "remembered": false
  },
  {
    "id": 56,
    "front": "Conference room",
    "back": "Sala konferencyjna",
    "frontExample": "The conference room fits fifty people.",
    "backExample": "Sala konferencyjna mieści pięćdziesiąt osób.",
    "phonetic": "/kənˈfɜrəns ˈrʊm/",
    "remembered": false
  },
  {
    "id": 57,
    "front": "Reception desk",
    "back": "Lada recepcyjna",
    "frontExample": "Please return the keys to the reception desk.",
    "backExample": "Proszę zwrócić klucze do lady recepcyjnej.",
    "phonetic": "/rɪˈsɛpʃən ˈdesk/",
    "remembered": false
  },
  {
    "id": 58,
    "front": "Hotel manager",
    "back": "Kierownik hotelu",
    "frontExample": "The hotel manager apologized for the noise.",
    "backExample": "Kierownik hotelu przeprosił za hałas.",
    "phonetic": "/ˈhoʊl ˈmænɪdʒər/",
    "remembered": false
  },
  {
    "id": 59,
    "front": "Customer",
    "back": "Klient",
    "frontExample": "Every customer gets a welcome postcard.",
    "backExample": "Każdy klient dostaje powitalną pocztówkę.",
    "phonetic": "/ˈkʌstəmər/",
    "remembered": false
  },
  {
    "id": 60,
    "front": "Customer service",
    "back": "Obsługa klienta",
    "frontExample": "Customer service handled the issue fast.",
    "backExample": "Obsługa klienta szybko rozwiązała problem.",
    "phonetic": "/ˈkʌstəmər ˈsɜrvɪs/",
    "remembered": false
  },
  {
    "id": 61,
    "front": "Complaint",
    "back": "Skarga",
    "frontExample": "I filed a complaint about the broken AC.",
    "backExample": "Złożyłem skargę na zepsutą klimatyzację.",
    "phonetic": "/kəmˈpleɪnt/",
    "remembered": false
  },
  {
    "id": 62,
    "front": "Solution",
    "back": "Rozwiązanie",
    "frontExample": "They offered a solution within minutes.",
    "backExample": "Zaproponowali rozwiązanie w ciągu kilku minut.",
    "phonetic": "/ˈsɑlʃən/",
    "remembered": false
  },
  {
    "id": 63,
    "front": "Reservation number",
    "back": "Numer rezerwacji",
    "frontExample": "Your reservation number is in the email.",
    "backExample": "Twój numer rezerwacji jest w wiadomości e-mail.",
    "phonetic": "/rɪˈzɛrvəˈʃən ˈnʌmər/",
    "remembered": false
  },
  {
    "id": 64,
    "front": "ID",
    "back": "Dowód osobisty",
    "frontExample": "Please show your ID at check-in.",
    "backExample": "Proszę okazać dowód osobisty przy zameldowaniu.",
    "phonetic": "/aɪˈdɪ/",
    "remembered": false
  },
  {
    "id": 65,
    "front": "Credit card",
    "back": "Karta kredytowa",
    "frontExample": "We guarantee the booking with a credit card.",
    "backExample": "Gwarantujemy rezerwację kartą kredytową.",
    "phonetic": "/ˈkredɪt ˈkɑd/",
    "remembered": false
  },
  {
    "id": 66,
    "front": "Cash",
    "back": "Gotówka",
    "frontExample": "You can pay the city tax in cash.",
    "backExample": "Podatek miejski możesz zapłacić gotówką.",
    "phonetic": "/kæʃ/",
    "remembered": false
  },
  {
    "id": 67,
    "front": "Invoice",
    "back": "Faktura",
    "frontExample": "I need an invoice for my company.",
    "backExample": "Potrzebuję faktury dla mojej firmy.",
    "phonetic": "/ɪnˈvɔɪs/",
    "remembered": false
  },
  {
    "id": 68,
    "front": "Receipt",
    "back": "Paragon",
    "frontExample": "Ask for a receipt at the bar.",
    "backExample": "Poproś o paragon w barze.",
    "phonetic": "/rɪˈsipt/",
    "remembered": false
  },
  {
    "id": 69,
    "front": "Deposit",
    "back": "Kaucja, zaliczka",
    "frontExample": "They require a 100-dollar deposit at check-in.",
    "backExample": "Wymagają kaucji w wysokości 100 dolarów przy zameldowaniu.",
    "phonetic": "/dɪˈpɑzɪt/",
    "remembered": false
  },
  {
    "id": 70,
    "front": "Cancelation",
    "back": "Anulowanie",
    "frontExample": "We requested cancelation due to illness.",
    "backExample": "Poprosiliśmy o anulowanie z powodu choroby.",
    "phonetic": "/kænsəˈleɪʃən/",
    "remembered": false
  },
  {
    "id": 71,
    "front": "Cancellation fee",
    "back": "Opłata za anulowanie",
    "frontExample": "There's a cancellation fee after 6 p.m.",
    "backExample": "Po 18:00 obowiązuje opłata za anulowanie.",
    "phonetic": "/kænsəˈleɪʃən ˈfeɪ/",
    "remembered": false
  },
  {
    "id": 72,
    "front": "Availability",
    "back": "Dostępność",
    "frontExample": "Check availability for next weekend.",
    "backExample": "Sprawdź dostępność na następny weekend.",
    "phonetic": "/əˈvæləbɪlɪtɪ/",
    "remembered": false
  },
  {
    "id": 73,
    "front": "Fully booked",
    "back": "Brak wolnych miejsc",
    "frontExample": "The hotel is fully booked for New Year's Eve.",
    "backExample": "Hotel jest w pełni zajęty w sylwestra.",
    "phonetic": "/ˈfʊlɪ ˈbʊkt/",
    "remembered": false
  },
  {
    "id": 74,
    "front": "View",
    "back": "Widok",
    "frontExample": "We paid extra for a better view.",
    "backExample": "Zapłaciliśmy więcej za lepszy widok.",
    "phonetic": "/vju/",
    "remembered": false
  },
  {
    "id": 75,
    "front": "Sea view",
    "back": "Widok na morze",
    "frontExample": "Our balcony has a sea view.",
    "backExample": "Nasz balkon ma widok na morze.",
    "phonetic": "/si ˈvju/",
    "remembered": false
  },
  {
    "id": 76,
    "front": "City view",
    "back": "Widok na miasto",
    "frontExample": "I prefer a city view at night.",
    "backExample": "Wolę widok na miasto nocą.",
    "phonetic": "/ˈsɪti ˈvju/",
    "remembered": false
  },
  {
    "id": 77,
    "front": "Mountain view",
    "back": "Widok na góry",
    "frontExample": "The suite offers a mountain view.",
    "backExample": "Apartament oferuje widok na góry.",
    "phonetic": "/ˈmaʊntən ˈvju/",
    "remembered": false
  },
  {
    "id": 78,
    "front": "Balcony",
    "back": "Balkon",
    "frontExample": "Smoking is not allowed on the balcony.",
    "backExample": "Na balkonie nie wolno palić.",
    "phonetic": "/ˈbælkənɪ/",
    "remembered": false
  },
  {
    "id": 79,
    "front": "Terrace",
    "back": "Taras",
    "frontExample": "Dinner is served on the terrace in summer.",
    "backExample": "Latem kolację podaje się na tarasie.",
    "phonetic": "/ˈtɛrəs/",
    "remembered": false
  },
  {
    "id": 80,
    "front": "Quiet",
    "back": "Cichy",
    "frontExample": "It's a quiet room at the end of the hall.",
    "backExample": "To cichy pokój na końcu korytarza.",
    "phonetic": "/ˈkwaɪət/",
    "remembered": false
  },
  {
    "id": 81,
    "front": "Noisy",
    "back": "Hałaśliwy",
    "frontExample": "The street is noisy after midnight.",
    "backExample": "Ulica jest głośna po północy.",
    "phonetic": "/ˈnɔɪzi/",
    "remembered": false
  },
  {
    "id": 82,
    "front": "Clean",
    "back": "Czysty",
    "frontExample": "The bathroom was perfectly clean.",
    "backExample": "Łazienka była idealnie czysta.",
    "phonetic": "/klin/",
    "remembered": false
  },
  {
    "id": 83,
    "front": "Dirty",
    "back": "Brudny",
    "frontExample": "The carpet looked dirty and worn.",
    "backExample": "Dywan wyglądał na brudny i zużyty.",
    "phonetic": "/ˈdɜːrti/",
    "remembered": false
  },
  {
    "id": 84,
    "front": "Comfortable",
    "back": "wygodny",
    "frontExample": "The chairs are comfortable for long meetings.",
    "backExample": "Krzesła są wygodne na długie spotkania.",
    "phonetic": "/ˈkɑmfərtəbl/",
    "remembered": false
  },
  {
    "id": 85,
    "front": "Uncomfortable",
    "back": "Niewygodny",
    "frontExample": "The sofa felt uncomfortable to sleep on.",
    "backExample": "Kanapa była niewygodna do spania.",
    "phonetic": "/ʌnˈkɑmfərtəbl/",
    "remembered": false
  },
  {
    "id": 86,
    "front": "Small",
    "back": "Mały",
    "frontExample": "The room is small but cozy.",
    "backExample": "Pokój jest mały, ale przytulny.",
    "phonetic": "/smɔl/",
    "remembered": false
  },
  {
    "id": 87,
    "front": "Big",
    "back": "Duży",
    "frontExample": "We got a big room with two windows.",
    "backExample": "Dostaliśmy duży pokój z dwoma oknami.",
    "phonetic": "/bɪɡ/",
    "remembered": false
  },
  {
    "id": 88,
    "front": "Broken",
    "back": "Zepsuty",
    "frontExample": "The safe is broken and won't close.",
    "backExample": "Sejf jest zepsuty i nie da się go zamknąć.",
    "phonetic": "/ˈbroʊkən/",
    "remembered": false
  },
  {
    "id": 89,
    "front": "Towels included",
    "back": "Ręczniki w cenie",
    "frontExample": "Are towels included in the price?",
    "backExample": "Czy ręczniki są wliczone w cenę?",
    "phonetic": "/ˈtəʊls ɪnˈklʌzd/",
    "remembered": false
  },
  {
    "id": 90,
    "front": "Free Wi-Fi",
    "back": "Darmowe Wi-Fi",
    "frontExample": "The lobby has free Wi-Fi.",
    "backExample": "W holu jest darmowe Wi-Fi.",
    "phonetic": "/fri ˈwifaɪ/",
    "remembered": false
  },
  {
    "id": 91,
    "front": "Free Parking",
    "back": "Darmowy parking",
    "frontExample": "Free parking is behind the hotel.",
    "backExample": "Darmowy parking jest za hotelem.",
    "phonetic": "/fri ˈpɑrkɪŋ/",
    "remembered": false
  },
  {
    "id": 92,
    "front": "Swimming pool",
    "back": "Basen",
    "frontExample": "The swimming pool is heated in winter.",
    "backExample": "Basen jest podgrzewany zimą.",
    "phonetic": "/ˈswɪmɪŋ ˈpʊl/",
    "remembered": false
  },
  {
    "id": 93,
    "front": "Gym",
    "back": "Siłownia",
    "frontExample": "The gym opens at 6 a.m. on weekdays.",
    "backExample": "Siłownia otwiera się o 6 rano w dni powszednie.",
    "phonetic": "/dʒɪm/",
    "remembered": false
  },
  {
    "id": 94,
    "front": "Spa",
    "back": "Spa, Uzdrowisko",
    "frontExample": "The spa offers couples treatments.",
    "backExample": "Spa oferuje zabiegi dla par.",
    "phonetic": "/spɑː/",
    "remembered": false
  },
  {
    "id": 95,
    "front": "Sauna",
    "back": "Sauna",
    "frontExample": "The sauna is mixed after 8 p.m.",
    "backExample": "Sauna jest koedukacyjna po 20:00.",
    "phonetic": "/ˈsunə/",
    "remembered": false
  },
  {
    "id": 96,
    "front": "Massage",
    "back": "Masaż",
    "frontExample": "I booked a deep tissue massage for Friday.",
    "backExample": "Zarezerwowałem masaż głębokotkankowy na piątek.",
    "phonetic": "/məˈsɑːʒ/",
    "remembered": false
  },
  {
    "id": 97,
    "front": "Tourist information",
    "back": "Informacja turystyczna",
    "frontExample": "Tourist information is next to the museum.",
    "backExample": "Informacja turystyczna jest obok muzeum.",
    "phonetic": "/ˈturɪst ɪnˈfɔrməʃən/",
    "remembered": false
  },
  {
    "id": 98,
    "front": "Map",
    "back": "Mapa",
    "frontExample": "Could you mark the hotel on the map?",
    "backExample": "Czy mógłbyś zaznaczyć hotel na mapie?",
    "phonetic": "/mæp/",
    "remembered": false
  },
  {
    "id": 99,
    "front": "City center",
    "back": "Centrum miasta",
    "frontExample": "A shuttle runs to the city center every hour.",
    "backExample": "Bus wahadłowy jeździ do centrum miasta co godzinę.",
    "phonetic": "/ˈsɪti ˈsɛntər/",
    "remembered": false
  }
]